evolve_words/__init__.py
evolve_words/__main__.py
evolve_words/app.py
evolve_words/py.typed
evolve_words-0.2.1.dist-info/METADATA
evolve_words-0.2.1.dist-info/WHEEL
evolve_words-0.2.1.dist-info/entry_points.txt
evolve_words-0.2.1.dist-info/top_level.txt
evolve_words-0.2.1.dist-info/RECORD
