Metadata-Version: 2.1
Name: evolve-words
Version: 0.2.1
Summary: A simple illustration of mutation aiding evolution
Home-page: https://github.com/davep/evolve-words
Author: Dave Pearson
Author-email: davep@davep.org
Maintainer: Dave Pearson
Maintainer-email: davep@davep.org
License: License :: OSI Approved :: GNU General Public License v3 or later (GPLv3+)
Project-URL: Documentation, https://github.com/davep/evolve-words/blob/main/README.md
Project-URL: Source, https://github.com/davep/evolve-words
Project-URL: Issues, https://github.com/davep/evolve-words/issues
Project-URL: Discussions, https://github.com/davep/evolve-words/discussions
Keywords: evolution,science,example,illustration
Classifier: License :: OSI Approved :: GNU General Public License v3 or later (GPLv3+)
Classifier: Environment :: Console
Classifier: Development Status :: 3 - Alpha
Classifier: Operating System :: OS Independent
Classifier: Programming Language :: Python :: 3.8
Classifier: Programming Language :: Python :: 3.9
Classifier: Programming Language :: Python :: 3.10
Classifier: Programming Language :: Python :: 3.11
Classifier: Programming Language :: Python :: 3.12
Classifier: Topic :: Terminals
Classifier: Typing :: Typed
Requires-Python: >=3.8
Requires-Dist: textual >=0.40.0
Requires-Dist: textual-plotext >=0.2.1
